create_server_app/AppConfig.py
create_server_app/__init__.py
create_server_app/app.py
create_server_app/cli.py
create_server_app/conftest.py
create_server_app/create_nextjs.py
create_server_app/create_server.py
create_server_app/dataChecker.py
create_server_app/mongoDb.py
create_server_app/objects.py
create_server_app/requirements.py
create_server_app/schemas.py
create_server_app/test_functions.py
create_server_app/updateSchema.py
create_server_app/utils.py
create_server_app/vscodeTasks.py
create_server_app-1.0.6.9.dist-info/LICENSE
create_server_app-1.0.6.9.dist-info/METADATA
create_server_app-1.0.6.9.dist-info/WHEEL
create_server_app-1.0.6.9.dist-info/entry_points.txt
create_server_app-1.0.6.9.dist-info/top_level.txt
create_server_app-1.0.6.9.dist-info/RECORD
