Metadata-Version: 2.1
Name: create-server-app
Version: 1.0.6.9
Summary: A CLI tool to create a server app project.
Home-page: https://github.com/FloresTristan/create-server-app
Author: Michael
Classifier: Programming Language :: Python :: 3.8
Classifier: License :: OSI Approved :: MIT License
Classifier: Operating System :: OS Independent
License-File: LICENSE
Requires-Dist: flask
Requires-Dist: pytest
Requires-Dist: pytest-cov
Requires-Dist: pymongo
